borg_space/__init__.py
borg_space/config.py
borg_space/main.py
borg_space-2.3.dist-info/entry_points.txt
borg_space-2.3.dist-info/licenses/LICENSE
borg_space-2.3.dist-info/WHEEL
borg_space-2.3.dist-info/METADATA
borg_space-2.3.dist-info/RECORD
