Metadata-Version: 2.4
Name: borg_space
Version: 2.3
Summary: Accessory for Emborg used to report and track the size of your Borg repositories
Keywords: emborg,borg,backups
Author-email: Ken Kundert <borg-space@nurdletech.com>
Requires-Python: >=3.6
Classifier: License :: OSI Approved :: GNU General Public License v3 or later (GPLv3+)
Classifier: Natural Language :: English
Classifier: Operating System :: POSIX :: Linux
Classifier: Programming Language :: Python :: 3
Classifier: Topic :: Utilities
License-File: LICENSE
Requires-Dist: appdirs
Requires-Dist: arrow
Requires-Dist: docopt
Requires-Dist: inform>=1.34
Requires-Dist: matplotlib
Requires-Dist: nestedtext
Requires-Dist: quantiphy
Requires-Dist: shlib
Requires-Dist: voluptuous>=0.14
Project-URL: changelog, https://github.com/KenKundert/ntlog/blob/master/CHANGELOG.rst
Project-URL: documentation, https://github.com/KenKundert/borg-space/blob/master/README.rst
Project-URL: homepage, https://github.com/kenkundert/borg-space
Project-URL: repository, https://github.com/kenkundert/borg-space
